hello/__init__.py
hello/cli.py
hello/core.py
hello/recipe/greeting.py
hello_quinx-0.2.0.dist-info/entry_points.txt
hello_quinx-0.2.0.dist-info/METADATA
hello_quinx-0.2.0.dist-info/WHEEL
hello_quinx-0.2.0.dist-info/RECORD
