Metadata-Version: 2.3
Name: hello_quinx
Version: 0.2.0
Summary: Learn how to publish a PyPI package
Author: Quynh Nguyen
Author-email: seriquynh@gmail.com
Requires-Python: >=3.9,<4.0
Classifier: Programming Language :: Python :: 3
Classifier: Programming Language :: Python :: 3.9
Classifier: Programming Language :: Python :: 3.10
Classifier: Programming Language :: Python :: 3.11
Classifier: Programming Language :: Python :: 3.12
Classifier: Programming Language :: Python :: 3.13
